MANIFEST.in
Makefile
README.md
olm_build.py
setup.cfg
setup.py
include/olm/olm.h
include/olm/pk.h
olm/__init__.py
olm/__version__.py
olm/_compat.py
olm/_finalize.py
olm/account.py
olm/group_session.py
olm/pk.py
olm/session.py
olm/utility.py
python_olm_harmonyqt.egg-info/PKG-INFO
python_olm_harmonyqt.egg-info/SOURCES.txt
python_olm_harmonyqt.egg-info/dependency_links.txt
python_olm_harmonyqt.egg-info/not-zip-safe
python_olm_harmonyqt.egg-info/requires.txt
python_olm_harmonyqt.egg-info/top_level.txt